inline_svg/__init__.py
inline_svg/__version__.py
inline_svg/config.py
inline_svg/plugin.py
inline_svg/util.py
mkdocs_inline_svg_plugin-0.1.5.dist-info/METADATA
mkdocs_inline_svg_plugin-0.1.5.dist-info/WHEEL
mkdocs_inline_svg_plugin-0.1.5.dist-info/entry_points.txt
mkdocs_inline_svg_plugin-0.1.5.dist-info/licenses/LICENSE.txt
mkdocs_inline_svg_plugin-0.1.5.dist-info/RECORD
