Metadata-Version: 2.3
Name: mkdocs-inline-svg-plugin
Version: 0.1.5
Summary: MkDocs plugin for inlining svg-href img tags
Project-URL: Documentation, https://github.com/oniboni/mkdocs-inline-svg-plugin#readme
Project-URL: Issues, https://github.com/oniboni/mkdocs-inline-svg-plugin/issues
Project-URL: Source, https://github.com/oniboni/mkdocs-inline-svg-plugin
Author-email: Oni Boni <oniboni@mailbox.org>
License-Expression: MIT
License-File: LICENSE.txt
Keywords: MkDocs
Classifier: Development Status :: 4 - Beta
Classifier: Programming Language :: Python
Classifier: Programming Language :: Python :: 3.8
Classifier: Programming Language :: Python :: 3.9
Classifier: Programming Language :: Python :: 3.10
Classifier: Programming Language :: Python :: 3.11
Classifier: Programming Language :: Python :: 3.12
Classifier: Programming Language :: Python :: Implementation :: CPython
Classifier: Programming Language :: Python :: Implementation :: PyPy
Requires-Python: >=3.8
Requires-Dist: beautifulsoup4~=4.12.0
Requires-Dist: mkdocs>=1.5.0
Requires-Dist: requests~=2.31.0
